<measure>
  <schema_version>3.0</schema_version>
  <name>hpxml_build_model</name>
  <uid>90f52d39-37a6-4ccf-9826-67acd7e44d86</uid>
  <version_id>6f5788c8-c24c-490f-9089-48b6bedf8b06</version_id>
  <version_modified>20170311T210550Z</version_modified>
  <xml_checksum>0D0748A3</xml_checksum>
  <class_name>HPXMLBuildModel</class_name>
  <display_name>HPXML Build Model</display_name>
  <description>E+ RESNET</description>
  <modeler_description>E+ RESNET</modeler_description>
  <arguments>
    <argument>
      <name>hpxml_directory</name>
      <display_name>HPXML Directory</display_name>
      <description>Absolute (or relative) directory to HPXML files.</description>
      <type>String</type>
      <required>true</required>
      <model_dependent>false</model_dependent>
      <default_value>./resources</default_value>
    </argument>
    <argument>
      <name>hpxml_file_name</name>
      <display_name>HPXML File Name</display_name>
      <description>Name of the HPXML file.</description>
      <type>String</type>
      <required>true</required>
      <model_dependent>false</model_dependent>
      <default_value>audit.xml</default_value>
    </argument>
    <argument>
      <name>measures_dir</name>
      <display_name>Residential Measures Directory</display_name>
      <description>Absolute (or relative) directory to residential measures.</description>
      <type>String</type>
      <required>true</required>
      <model_dependent>false</model_dependent>
    </argument>
  </arguments>
  <outputs/>
  <provenances/>
  <tags>
    <tag>Whole Building.Space Types</tag>
  </tags>
  <attributes>
    <attribute>
      <name>Measure Type</name>
      <value>ModelMeasure</value>
      <datatype>string</datatype>
    </attribute>
    <attribute>
      <name>Intended Software Tool</name>
      <value>Apply Measure Now</value>
      <datatype>string</datatype>
    </attribute>
    <attribute>
      <name>Intended Software Tool</name>
      <value>OpenStudio Application</value>
      <datatype>string</datatype>
    </attribute>
    <attribute>
      <name>Intended Software Tool</name>
      <value>Parametric Analysis Tool</value>
      <datatype>string</datatype>
    </attribute>
  </attributes>
  <files>
    <file>
      <filename>audit.xml</filename>
      <filetype>xml</filetype>
      <usage_type>resource</usage_type>
      <checksum>505846B0</checksum>
    </file>
    <file>
      <filename>helper_methods.rb</filename>
      <filetype>rb</filetype>
      <usage_type>resource</usage_type>
      <checksum>25ED0CF7</checksum>
    </file>
    <file>
      <version>
        <software_program>OpenStudio</software_program>
        <identifier>1.14.0</identifier>
        <min_compatible>2.0.4</min_compatible>
      </version>
      <filename>measure.rb</filename>
      <filetype>rb</filetype>
      <usage_type>script</usage_type>
      <checksum>F9404692</checksum>
    </file>
    <file>
      <filename>hpxml_build_model_test.rb</filename>
      <filetype>rb</filetype>
      <usage_type>test</usage_type>
      <checksum>AC7B534A</checksum>
    </file>
  </files>
</measure>
